Workbook
Name Slicer_Region: #N/A
Name Slicer_Years: #N/A

Sheet Sheet2
A3: Sum of Total Sales | B3: Sum of Units Sold | C3: Average of Price per Unit | D3: Sum of Operating Profit
A4: 362963.2 | B4: 903220 | C4: 0.38263889 | D4: 149477.23
A6: Sum of Total Sales | B6: Column Labels
A7: Row Labels | B7: 2022 | C7: 2023 | D7: Grand Total
A8: Coca-Cola | B8: 60321 | C8: 344505.1 | D8: 404826.1
A9: Dasani Water | B9: 71477.9 | C9: 351015.8 | D9: 422493.7
A10: Diet Coke | B10: 68447.2 | C10: 296257.3 | D10: 364704.5
A11: Fanta | B11: 51799.9 | C11: 211109.8 | D11: 262909.7
A12: Powerade | B12: 47181.9 | C12: 233937.5 | D12: 281119.4
A13: Sprite | B13: 63735.3 | C13: 260546.9 | D13: 324282.2
A14: Grand Total | B14: 362963.2 | C14: 1697372.4 | D14: 2060335.6
A16: Sum of Total Sales | B16: Column Labels
A17: Row Labels | B17: 2022 | C17: 2023 | D17: Grand Total
A18: Amazon | B18: 27325 | C18: 5809.1 | D18: 33134.1
A19: BevCo | C19: 132245 | D19: 132245
A20: FizzyCo | B20: 41267.9 | C20: 860704.2 | D20: 901972.1
A21: Target | C21: 50668 | D21: 50668
A22: Walmart | B22: 273562 | C22: 197706.3 | D22: 471268.3
A23: West Soda | B23: 20808.3 | C23: 450239.8 | D23: 471048.1
A24: Grand Total | B24: 362963.2 | C24: 1697372.4 | D24: 2060335.6
A26: Years | B26: Quarters | C26: Sum of Total Sales | D26: Average of Operating Margin
A27: 2022 | B27: Qtr1 | C27: 692776.1 | D27: 0.40174684 | E27: =A27 -> 2022 | F27: =B27 -> Qtr1 | G27: =C27 -> 692776.1 | H27: =D27 -> 0.40174684
B28: Qtr2 | C28: 644203.9 | D28: 0.4 | F28: =B28 -> Qtr2 | G28: =C28 -> 644203.9 | H28: =D28 -> 0.4
B29: Qtr3 | C29: 719170.4 | D29: 0.41026549 | F29: =B29 -> Qtr3 | G29: =C29 -> 719170.4 | H29: =D29 -> 0.41026549
B30: Qtr4 | C30: 367582.1 | D30: 0.40243816 | F30: =B30 -> Qtr4 | G30: =C30 -> 367582.1 | H30: =D30 -> 0.40243816
A31: 2023 | B31: Qtr1 | C31: 1877584.3 | D31: 0.41657045 | E31: =A31 -> 2023 | F31: =B31 -> Qtr1 | G31: =C31 -> 1877584.3 | H31: =D31 -> 0.41657045
B32: Qtr2 | C32: 2379424.8 | D32: 0.42755819 | F32: =B32 -> Qtr2 | G32: =C32 -> 2379424.8 | H32: =D32 -> 0.42755819
B33: Qtr3 | C33: 2805752.5 | D33: 0.4347017 | F33: =B33 -> Qtr3 | G33: =C33 -> 2805752.5 | H33: =D33 -> 0.4347017
B34: Qtr4 | C34: 2530170.9 | D34: 0.42483933 | F34: =B34 -> Qtr4 | G34: =C34 -> 2530170.9 | H34: =D34 -> 0.42483933
A35: Grand Total | C35: 12016665 | D35: 0.42299129

Sheet Data
B2: Retailer Dataset
B4: Retailer | C4: Retailer ID | D4: Invoice Date | E4: Region | F4: State | G4: City | H4: Beverage Brand | I4: Price per Unit | J4: Units Sold | K4: Total Sales | L4: Operating Profit | M4: Operating Margin
B5: BevCo | C5: 1185732 | D5: 44562 | E5: Northeast | F5: New York | G5: New York | H5: Coca-Cola | I5: 0.5 | J5: 12000 | K5: 6000 | L5: 3000 | M5: 0.5
B6: BevCo | C6: 1185732 | D6: 44563 | E6: Northeast | F6: New York | G6: New York | H6: Diet Coke | I6: 0.5 | J6: 10000 | K6: 5000 | L6: 1500 | M6: 0.3
B7: BevCo | C7: 1185732 | D7: 44564 | E7: Northeast | F7: New York | G7: New York | H7: Sprite | I7: 0.4 | J7: 10000 | K7: 4000 | L7: 1400 | M7: 0.35
B8: BevCo | C8: 1185732 | D8: 44565 | E8: Northeast | F8: New York | G8: New York | H8: Fanta | I8: 0.45 | J8: 8500 | K8: 3825 | L8: 1338.75 | M8: 0.35
B9: BevCo | C9: 1185732 | D9: 44566 | E9: Northeast | F9: New York | G9: New York | H9: Powerade | I9: 0.6 | J9: 9000 | K9: 5400 | L9: 1620 | M9: 0.3
B10: BevCo | C10: 1185732 | D10: 44567 | E10: Northeast | F10: New York | G10: New York | H10: Dasani Water | I10: 0.5 | J10: 10000 | K10: 5000 | L10: 1250 | M10: 0.25
B11: BevCo | C11: 1185732 | D11: 44568 | E11: Northeast | F11: New York | G11: New York | H11: Coca-Cola | I11: 0.5 | J11: 12500 | K11: 6250 | L11: 3125 | M11: 0.5
B12: BevCo | C12: 1185732 | D12: 44569 | E12: Northeast | F12: New York | G12: New York | H12: Diet Coke | I12: 0.5 | J12: 9000 | K12: 4500 | L12: 1350 | M12: 0.3
B13: BevCo | C13: 1185732 | D13: 44582 | E13: Northeast | F13: New York | G13: New York | H13: Sprite | I13: 0.4 | J13: 9500 | K13: 3800 | L13: 1330 | M13: 0.35
B14: BevCo | C14: 1185732 | D14: 44583 | E14: Northeast | F14: New York | G14: New York | H14: Fanta | I14: 0.45 | J14: 8250 | K14: 3712.5 | L14: 1299.375 | M14: 0.35
B15: BevCo | C15: 1185732 | D15: 44584 | E15: Northeast | F15: New York | G15: New York | H15: Powerade | I15: 0.6 | J15: 9000 | K15: 5400 | L15: 1620 | M15: 0.3
B16: BevCo | C16: 1185732 | D16: 44585 | E16: Northeast | F16: New York | G16: New York | H16: Dasani Water | I16: 0.5 | J16: 10000 | K16: 5000 | L16: 1250 | M16: 0.25
... B9652: BevCo | C9652: 1185732 | D9652: 44979 | E9652: Northeast | F9652: New Hampshire | G9652: Manchester | H9652: Sprite | I9652: 0.29 | J9652: 830 | K9652: 240.7 | L9652: 64.989 | M9652: 0.27

Sheet Dashboard
C9: Sales by Beverage Brand | H9: Sales by Retailer
C10: Brand | D10: Sales 2022 | E10: Sales 2023 | F10: Varience | H10: Retailer | I10: Sales 2022 | J10: Sales 2023 | K10: Varience
C11: =Sheet2!A18 -> Amazon | D11: =Sheet2!B18 -> 27325 | E11: =Sheet2!C18 -> 5809.1 | F11: =E11-D11 -> -21515.9 | H11: =Sheet2!A18 -> Amazon | I11: =Sheet2!B18 -> 27325 | J11: =Sheet2!C18 -> 5809.1 | K11: =Sheet2!D18 -> 33134.1
C12: =Sheet2!A19 -> BevCo | D12: =Sheet2!B19 -> 0 | E12: =Sheet2!C19 -> 132245 | F12: =E12-D12 -> 132245 | H12: =Sheet2!A19 -> BevCo | I12: =Sheet2!B19 -> 0 | J12: =Sheet2!C19 -> 132245 | K12: =Sheet2!D19 -> 132245
C13: =Sheet2!A20 -> FizzyCo | D13: =Sheet2!B20 -> 41267.9 | E13: =Sheet2!C20 -> 860704.2 | F13: =E13-D13 -> 819436.3 | H13: =Sheet2!A20 -> FizzyCo | I13: =Sheet2!B20 -> 41267.9 | J13: =Sheet2!C20 -> 860704.2 | K13: =Sheet2!D20 -> 901972.1
C14: =Sheet2!A21 -> Target | D14: =Sheet2!B21 -> 0 | E14: =Sheet2!C21 -> 50668 | F14: =E14-D14 -> 50668 | H14: =Sheet2!A21 -> Target | I14: =Sheet2!B21 -> 0 | J14: =Sheet2!C21 -> 50668 | K14: =Sheet2!D21 -> 50668
C15: =Sheet2!A22 -> Walmart | D15: =Sheet2!B22 -> 273562 | E15: =Sheet2!C22 -> 197706.3 | F15: =E15-D15 -> -75855.7 | H15: =Sheet2!A22 -> Walmart | I15: =Sheet2!B22 -> 273562 | J15: =Sheet2!C22 -> 197706.3 | K15: =Sheet2!D22 -> 471268.3
C16: =Sheet2!A23 -> West Soda | D16: =Sheet2!B23 -> 20808.3 | E16: =Sheet2!C23 -> 450239.8 | F16: =E16-D16 -> 429431.5 | H16: =Sheet2!A23 -> West Soda | I16: =Sheet2!B23 -> 20808.3 | J16: =Sheet2!C23 -> 450239.8 | K16: =Sheet2!D23 -> 471048.1
C17: Total | D17: =Sheet2!B24 -> 362963.2 | E17: =Sheet2!C24 -> 1697372.4 | F17: =E17-D17 -> 1334409.2 | H17: Total | I17: =Sheet2!B24 -> 362963.2 | J17: =Sheet2!C24 -> 1697372.4 | K17: =Sheet2!D24 -> 2060335.6
C20: Sales and Operating Profit Margin by Quarter
